label_flatten/__init__.py
label_flatten/node.py
label_flatten/tree.py
label_flatten/writer.py
label_flatten-0.1.3.dist-info/METADATA
label_flatten-0.1.3.dist-info/WHEEL
label_flatten-0.1.3.dist-info/licenses/LICENSE
label_flatten-0.1.3.dist-info/RECORD
