Metadata-Version: 2.1
Name: label_flatten
Version: 0.1.3
Summary: Flatten hierarchical concepts or labels system to declarative sentences and labels.
Project-URL: Homepage, https://github.com/fireindark707/label_flatten
Project-URL: Bug Tracker, https://github.com/fireindark707/label_flatten/issues
Author-email: phoenix000 <phoenix000.taipei@gmail.com>
License-File: LICENSE
Classifier: License :: OSI Approved :: MIT License
Classifier: Operating System :: OS Independent
Classifier: Programming Language :: Python :: 3
Requires-Python: >=3.6
